{
	"id": "aef9dc65-ee60-495f-b68b-261929818c23",
	"name": "PetStore",
	"values": [
		{
			"key": "baseurl",
			"value": "https://petstore.swagger.io/v2",
			"type": "default",
			"enabled": true
		},
		{
			"key": "userId",
			"value": "",
			"type": "any",
			"enabled": true
		},
		{
			"key": "username",
			"value": "",
			"type": "any",
			"enabled": true
		},
		{
			"key": "dynamicUsername",
			"value": "",
			"type": "any",
			"enabled": true
		}
	],
	"_postman_variable_scope": "environment",
	"_postman_exported_at": "2024-07-14T10:13:54.043Z",
	"_postman_exported_using": "Postman/11.3.2"
}